memora/__init__.py
memora/cache.py
memora/config.py
memora/core.py
memora/decorators.py
memora/scheduler.py
memora/types.py
memora_cache-0.1.0.dist-info/licenses/LICENSE
memora_cache-0.1.0.dist-info/METADATA
memora_cache-0.1.0.dist-info/WHEEL
memora_cache-0.1.0.dist-info/top_level.txt
memora_cache-0.1.0.dist-info/RECORD
