Metadata-Version: 2.4
Name: memora-cache
Version: 0.1.0
Summary: Semantic caching for LLMs
Author: Juan José de las Heras Herrera
Requires-Python: >=3.12
License-File: LICENSE
Requires-Dist: lancedb>=0.25.1
Requires-Dist: orjson>=3.11.3
Requires-Dist: pyarrow>=21.0.0
Requires-Dist: sentence-transformers[onnx]>=5.1.1
Requires-Dist: structlog>=25.4.0
Provides-Extra: dev
Requires-Dist: pytest>=7.4.0; extra == "dev"
Requires-Dist: pytest-cov>=4.1.0; extra == "dev"
Dynamic: license-file
